petstore/__init__.py
petstore/api_helper.py
petstore/configuration.py
petstore/petstore_client.py
petstore/controllers/__init__.py
petstore/controllers/base_controller.py
petstore/controllers/pets_controller.py
petstore/exceptions/__init__.py
petstore/exceptions/api_exception.py
petstore/exceptions/error_exception.py
petstore/http/__init__.py
petstore/http/http_call_back.py
petstore/http/http_method_enum.py
petstore/http/http_request.py
petstore/http/http_response.py
petstore/http/auth/__init__.py
petstore/http/auth/o_auth_2.py
petstore/models/__init__.py
petstore/models/new_pet.py
petstore/models/pet.py
petstore/models/pet_type_enum.py
petstore/utilities/__init__.py
petstore/utilities/file_wrapper.py
demo_1_sdk-1.1.0.dist-info/LICENSE
demo_1_sdk-1.1.0.dist-info/METADATA
demo_1_sdk-1.1.0.dist-info/WHEEL
demo_1_sdk-1.1.0.dist-info/top_level.txt
demo_1_sdk-1.1.0.dist-info/RECORD
